Workbook
Name DESCRIPTION_1: #REF!
Name Flanges: #REF!
Name ID: #REF!
Name POWER_FUEL_SOURCE: #REF!
Name PowerOrFuelSource: #REF!
Name SUB_ASSY: #REF!
Name Valves: #REF!
Name WATER_SOURCE: #REF!
Name WaterSource: #REF!

Sheet Job BOM
A1: WATER SUPPLY & APPLICATION QUOTATION
A2: QUOTE REF | B2: 111885 | F2: CUSTOMER ID
A3: DATE | F3: CUSTOMER NAME
H4: EX-GST
A5: SUB-ASSY | B5: CC | C5: SUPPLIER | D5: SUPPLIER PT NO | E5: COWAG PT NO | F5: DESCRIPTION | G5: QTY | H5: COST EA | I5: COST TOTAL | J5: MARK-UP % | K5: SELL EA | L5: SELL TOTAL | M5: MARGIN $ | N5: MARGIN % | O5: Notes
F6: RT60 - OPTION 1
F7: RT60 - ZINCALUME | G7: 1 | H7: 8721.82 | I7: =G7*H7 -> 8721.82 | K7: 9690.91 | L7: =SUM(G7*K7) -> 9690.91 | M7: =L7-I7 -> 969.09 | N7: =M7/L7 -> 0.099999897
F8: RT60 - COLORBOND | G8: 1 | H8: 9572.73 | I8: =G8*H8 -> 9572.73 | K8: 10636.36 | L8: =SUM(G8*K8) -> 10636.36 | M8: =L8-I8 -> 1063.63 | N8: =M8/L8 -> 0.099999436
F9: DELIVERY | G9: 1 | H9: 272.73 | I9: =G9*H9 -> 272.73 | K9: 272.73 | L9: =SUM(G9*K9) -> 272.73 | M9: =L9-I9 -> 0 | N9: =M9/L9 -> 0
E10: FREE | F10: VERMIN / FIRE OUTLET / LEVEL GUAGE | G10: 1 | H10: 0 | I10: 0 | K10: 0 | L10: =SUM(G10*K10) -> 0 | M10: =L10-I10 -> 0 | N10: =M10/L10 -> #DIV/0!
F11: WATER DELIVERY | G11: 1 | H11: 340 | I11: =G11*H11 -> 340 | K11: 380 | L11: =SUM(G11*K11) -> 380 | M11: =L11-I11 -> 40 | N11: =M11/L11 -> 0.10526316
F12: BLUEMETAL + DELIVERY ONLY | G12: 1 | H12: 270 | I12: =G12*H12 -> 270 | K12: 350 | L12: =SUM(G12*K12) -> 350 | M12: =L12-I12 -> 80 | N12: =M12/L12 -> 0.22857143
F13: RT100 - OPTION 2
F14: RT100 - ZINCALUME | G14: 1 | H14: 11004.55 | I14: =G14*H14 -> 11004.55 | K14: 12227.2 | L14: =SUM(G14*K14) -> 12227.2 | M14: =L14-I14 -> 1222.65 | N14: =M14/L14 -> 0.099994275
F15: RT100 - COLORBOND | G15: 1 | H15: 12002.73 | I15: =G15*H15 -> 12002.73 | K15: 13336.36 | L15: =SUM(G15*K15) -> 13336.36 | M15: =L15-I15 -> 1333.63 | N15: =M15/L15 -> 0.09999955
F16: DELIVERY | G16: 1 | H16: 272.73 | I16: =G16*H16 -> 272.73 | K16: 272.73 | L16: =SUM(G16*K16) -> 272.73 | M16: =L16-I16 -> 0 | N16: =M16/L16 -> 0
E17: FREE | F17: VERMIN / FIRE OUTLET / LEVEL GUAGE | G17: 1 | H17: 0 | I17: 0 | K17: 0 | L17: =SUM(G17*K17) -> 0 | M17: =L17-I17 -> 0 | N17: =M17/L17 -> #DIV/0!
F18: WATER DELIVERY | G18: 1 | H18: 340 | I18: =G18*H18 -> 340 | K18: 380 | L18: =SUM(G18*K18) -> 380 | M18: =L18-I18 -> 40 | N18: =M18/L18 -> 0.10526316
F19: BLUEMETAL + DELIVERY ONLY | G19: 1 | H19: 300 | I19: =G19*H19 -> 300 | K19: 380 | L19: =SUM(G19*K19) -> 380 | M19: =L19-I19 -> 80 | N19: =M19/L19 -> 0.21052632
G20: 0 | H20: 0 | I20: =G20*H20 -> 0 | K20: =SUM(H20*J20) -> 0 | L20: =SUM(G20*K20) -> 0 | M20: =L20-I20 -> 0 | N20: =M20/L20 -> #DIV/0!
F21: RT160 - OPTION 3
F22: RT160 - ZINCALUME | G22: 1 | H22: 15381.82 | I22: =G22*H22 -> 15381.82 | K22: 17090.91 | L22: =SUM(G22*K22) -> 17090.91 | M22: =L22-I22 -> 1709.09 | N22: =M22/L22 -> 0.099999941
F23: RT160 - COLORBOND | G23: 1 | H23: 16715.45 | I23: =G23*H23 -> 16715.45 | K23: 18572.73 | L23: =SUM(G23*K23) -> 18572.73 | M23: =L23-I23 -> 1857.28 | N23: =M23/L23 -> 0.10000038
F24: DELIVERY | G24: 1 | H24: 272.73 | I24: =G24*H24 -> 272.73 | K24: 272.73 | L24: =SUM(G24*K24) -> 272.73 | M24: =L24-I24 -> 0 | N24: =M24/L24 -> 0
E25: FREE | F25: VERMIN / FIRE OUTLET / LEVEL GUAGE | G25: 1 | H25: 0 | I25: 0 | K25: 0 | L25: =SUM(G25*K25) -> 0 | M25: =L25-I25 -> 0 | N25: =M25/L25 -> #DIV/0!
F26: WATER DELIVERY | G26: 1 | H26: 340 | I26: =G26*H26 -> 340 | K26: 380 | L26: =SUM(G26*K26) -> 380 | M26: =L26-I26 -> 40 | N26: =M26/L26 -> 0.10526316
F27: BLUEMETAL + DELIVERY ONLY | G27: 1 | H27: 360 | I27: =G27*H27 -> 360 | K27: 430 | L27: =SUM(G27*K27) -> 430 | M27: =L27-I27 -> 70 | N27: =M27/L27 -> 0.1627907

Sheet Quotation
A9: Lot 33, Bussell Hwy, Cowaramup. WA 6284
A10: Local Knowledge 50 Years and counting..
A12: Cowaramup Agencies supply to various local industries, including Vineyards, Wineries, Dairies, Commercial Farms and Resorts/Hotels. As an Independent Agribusiness, Cowaramup Agencies have a unique capacity to service the local area with supply and services ranging from Agronomy to Fencing and Trellising Products to Viticulture and Winery. Cowaramup Agencies have a wide range products including Crop Protection and Pest Control, Fertiliser/s, Seed and Animal Health. Cowaramup Agencies also have a dedicated Water Division with a high quality installer of customised Iron Filtration Systems plus Irrigation Systems specialising in Electrofusion and Poly Weld applications; standard PVC pipe, poly pipe, fittings, sprinklers, cables, pumps, as well as many other products that will help you to meet all your installation and maintenance requirements.
A21: Estimate #114693
A24: 10th August 2026
A27: Dear Craig,
A29: Thank you for your interest in Cowaramup Agencies and allowing me to quote on your proposed works. In the following pages, I have detailed the Scope of Works and Supply that I am quoting you. This detail shows inclusions specific site location detail, applicable specifications and details of the materials that will be supplied to complete your job. I will contact you to discuss this quote further and answer any questions you may have. I also invite you to contact the Cowaramup Agencies office should you have any queries or wish to adjust the requested supply, work or specifications. To confirm the following quotation, revise or proceed with any works, please contact myself or the Cowaramup Agencies office within the valid quotation period as noted enclosed.
A44: Regards,
A51: Simon Earl
A53: 0422 497343
A54: On Behalf of Cowaramup Agencies
A62: Customer Details | G62: Delivery Details
A63: Name | B63: Craig Lawson | G63: Address | H63: 899 Metricup Road
A64: Phone | H64: Wilyabrup
A65: Mobile | B65: 0420940607
A66: Email | B66: lawson.build@gmail.com | G66: Start Date | H66: TBC
A68: Scope of Works and Supply
A69: Proposal:
A70: Supply & Installation of Kingspan Steel Water Tank - Supply and installation of a selected Kingspan Steel Water Tank. - Tank supplied complete with FREE vermin-proofing, water level gauge and 50mm fire-fighting outlet. - Supply only of blue metal to be placed around the base of the tank following installation. - Supply and delivery of 12kL of water on the day of installation to assist in holding the tank liner in position during the initial filling process. Exclusions The following items are not included in this quotation: - Supply or installation of a sand pad. (A separate quotation can be provided upon request.) - Plumbing connections into or out of the water tank. - Supply and installation of pumps, UV filtration systems, or associated plumbing. (Separate quotations can be provided if required.)
A84: Quoted Price
I86: Ex-GST | K86: Total Inc-GST
A87: Option 1 - RT60
A88: RT60 - Zincalume | I88: =SUM('Job BOM'!L7,'Job BOM'!L9) -> 9963.64 | K88: =I88*1.1 -> 10960.004
A89: RT60 - Colorbond | I89: =SUM('Job BOM'!L8,'Job BOM'!L9) -> 10909.09 | K89: =I89*1.1 -> 11999.999
A90: Bluemetal & Delivery only | I90: ='Job BOM'!L12 -> 350 | K90: =I90*1.1 -> 385
A91: Option 2 - RT100
A92: RT100 - Zincalume | I92: =SUM('Job BOM'!L14,'Job BOM'!L16) -> 12499.93 | K92: =I92*1.1 -> 13749.923
A93: RT100 - Colorbond | I93: =SUM('Job BOM'!L15,'Job BOM'!L16) -> 13609.09 | K93: =I93*1.1 -> 14969.999
A94: Bluemetal & Delivery only | I94: ='Job BOM'!L19 -> 380 | K94: =I94*1.1 -> 418
A95: Option 3 - RT160
A96: RT160 - Zincalume | I96: =SUM('Job BOM'!L22,'Job BOM'!L24) -> 17363.64 | K96: =I96*1.1 -> 19100.004
A97: RT160 - Colorbond | I97: =SUM('Job BOM'!L23,'Job BOM'!L24) -> 18845.46 | K97: =I97*1.1 -> 20730.006
A98: Bluemetal & Delivery only | I98: ='Job BOM'!L27 -> 430 | K98: =I98*1.1 -> 473
A99: Water Cartage for all tanks
A100: Water Cartage | I100: ='Job BOM'!K26 -> 380 | K100: =I100*1.1 -> 418
A109: Pricing and Payment Terms
A111: Order Confirmation Deposit 50%
A112: Balance due on completion of work
A114: Quotation is valid for 14 days from date of issue.
A115: Prices quoted are CONFIDENTIAL and are not to be distributed to any third party.
A116: Quoted prices are valid on acceptance of full quote only.
A117: This quote is for estimation purposes only and may be subject to change without notice.
A119: Please note: While all due care and consideration has been taken to ensure estimation accuracy, due to the nature of the services provided there may be variations to final costs incurred. We will endeavour to limit any variations and keep you up to date on any changes as they occur.
A126: Additional Charges for most common issues
A127: HARD DIGGINGS: If, when excavating the site, the company discovers any obstacles or hard diggings that require the hire of machinery or extra labour, such as jack hammering, or rock breaking etc., the customer will pay these extra costs in addition to the Agreement price. | G127: APPROVAL FEES: If approval for any building can only be obtained with amendments or additional information, thus incurring additional costs as required by the local council or certifier, the customer will pay all the extra costs associated.
A128: HIDDEN OBSTRUCTIONS: If, during construction, services are damaged requiring repair such as Telstra, Electrical, Storm water etc., the customer will pay the costs associated with the repair in addition to the Agreement price. It is the customer's responsibility to advise the company of the existence of any such obstructions and to arrange (and pay any associated costs) for the location of same. | G128: SITE CLEAN UP: If the customer requires the company to remove the packaging or left over materials and any soil/rubbish associated with the works, from the site, unless noted otherwise in the Agreement the customer will pay these costs including labour and dump fees in addition to the Agreement price.
A129: DELAY IN DELIVERY: If the company considers that it is likely that it will not keep to the agreed delivery date, it shall without delay notify the customer of this and also state the reasons for the delay and the time at which it is estimated that the delivery can be made. | G129: PERMITS/LICENCES: If any part or part of the property pertinent to the quote requires building permits, or licences and permits of any kind, they are to be arranged by the customer at their expense.
A130: WARRANTY: Any warranty on faulty materials is fully dependent on suppliers' warranty to us. Generally, no warranty on labour is applicable. All travel and labour to repair will be done at client's cost unless otherwise specified.
A131: Please refer to our Terms and Conditions of Sale
